nomadjack
