Metadata-Version: 2.1
Name: nomadjack
Version: 0.0.2
Summary: Sidecar container to run arbitrary scripts inside nomad container
Home-page: https://github.com/yogeshraja/nomadjack
Author: Yogeshwaran Rajendran
Author-email: xxx@gmail.com
License: MIT
Keywords: nomadjack nomad
Platform: any
Classifier: Development Status :: 3 - Alpha
Classifier: Intended Audience :: Developers
Classifier: Programming Language :: Python
Classifier: Programming Language :: Python :: 3.6
Classifier: License :: OSI Approved :: MIT License
Classifier: Operating System :: OS Independent
Classifier: Topic :: Internet :: WWW/HTTP
Classifier: Topic :: Text Editors :: Text Processing
Classifier: Topic :: Software Development :: Libraries :: Python Modules
Classifier: Topic :: Utilities
Requires-Python: >=3.6
License-File: LICENSE
Requires-Dist: flask
Requires-Dist: flask-parameter-validation
Requires-Dist: flask-httpauth
Requires-Dist: docker
